pytest_selenium_auto/__init__.py
pytest_selenium_auto/browser_settings.py
pytest_selenium_auto/configuration_loader.py
pytest_selenium_auto/listener.py
pytest_selenium_auto/logger.py
pytest_selenium_auto/markers.py
pytest_selenium_auto/plugin.py
pytest_selenium_auto/utils.py
pytest_selenium_auto/wrappers.py
pytest_selenium_auto/.pytest_cache/.gitignore
pytest_selenium_auto/.pytest_cache/CACHEDIR.TAG
pytest_selenium_auto/.pytest_cache/README.md
pytest_selenium_auto/.pytest_cache/v/cache/nodeids
pytest_selenium_auto/.pytest_cache/v/cache/stepwise
pytest_selenium_auto/resources/error.png
pytest_selenium_auto/resources/style.css
pytest_selenium_auto-1.3.1.dist-info/entry_points.txt
pytest_selenium_auto-1.3.1.dist-info/WHEEL
pytest_selenium_auto-1.3.1.dist-info/METADATA
pytest_selenium_auto-1.3.1.dist-info/RECORD
